{
  "epoch:46": {
    "acc: ": 74.96,
    "f1: ": 0.75,
    "auc: ": 0.933
  },
  "epoch:47": {
    "acc: ": 74.14,
    "f1: ": 0.741,
    "auc: ": 0.929
  },
  "epoch:49": {
    "acc: ": 74.14,
    "f1: ": 0.742,
    "auc: ": 0.928
  },
  "epoch:44": {
    "acc: ": 74.04,
    "f1: ": 0.74,
    "auc: ": 0.929
  },
  "epoch:48": {
    "acc: ": 73.71,
    "f1: ": 0.738,
    "auc: ": 0.927
  },
  "epoch:40": {
    "acc: ": 73.57,
    "f1: ": 0.736,
    "auc: ": 0.924
  },
  "epoch:45": {
    "acc: ": 73.5,
    "f1: ": 0.735,
    "auc: ": 0.925
  },
  "epoch:43": {
    "acc: ": 72.93,
    "f1: ": 0.732,
    "auc: ": 0.924
  },
  "epoch:42": {
    "acc: ": 71.79,
    "f1: ": 0.714,
    "auc: ": 0.928
  },
  "epoch:41": {
    "acc: ": 71.5,
    "f1: ": 0.715,
    "auc: ": 0.917
  },
  "best10_mean": 73.428,
  "best10_f1_mean": 0.7343,
  "best10_auc_mean": 0.9264000000000001
}