{
  "epoch:37": {
    "acc: ": 93.1,
    "f1: ": 0.91,
    "auc: ": 0.996
  },
  "epoch:33": {
    "acc: ": 92.93,
    "f1: ": 0.907,
    "auc: ": 0.995
  },
  "epoch:27": {
    "acc: ": 91.74,
    "f1: ": 0.892,
    "auc: ": 0.994
  },
  "epoch:35": {
    "acc: ": 91.68,
    "f1: ": 0.895,
    "auc: ": 0.994
  },
  "epoch:41": {
    "acc: ": 91.41,
    "f1: ": 0.89,
    "auc: ": 0.994
  },
  "epoch:48": {
    "acc: ": 91.32,
    "f1: ": 0.889,
    "auc: ": 0.994
  },
  "epoch:49": {
    "acc: ": 91.11,
    "f1: ": 0.886,
    "auc: ": 0.993
  },
  "epoch:18": {
    "acc: ": 91.08,
    "f1: ": 0.873,
    "auc: ": 0.993
  },
  "epoch:46": {
    "acc: ": 91.08,
    "f1: ": 0.886,
    "auc: ": 0.993
  },
  "epoch:36": {
    "acc: ": 91.05,
    "f1: ": 0.885,
    "auc: ": 0.994
  },
  "best10_mean": 91.65,
  "best10_f1_mean": 0.8913,
  "best10_auc_mean": 0.994
}